MANIFEST.in
README.rst
setup.py
djhcup_core/__init__.py
djhcup_core/admin.py
djhcup_core/defaults.py
djhcup_core/models.py
djhcup_core/settings.py
djhcup_core/tests.py
djhcup_core/urls.py
djhcup_core/utils.py
djhcup_core/views.py
djhcup_core.egg-info/PKG-INFO
djhcup_core.egg-info/SOURCES.txt
djhcup_core.egg-info/dependency_links.txt
djhcup_core.egg-info/top_level.txt
djhcup_core/templates/djhcup_base.html
djhcup_core/templates/djhcup_core_index.html