Metadata-Version: 1.1
Name: djhcup_core
Version: 0.1
Summary: A django-based interface for warehousing HCUP data
Home-page: UNKNOWN
Author: T.J. Biel
Author-email: tbiel@med.umich.edu
License: MIT
Keywords: HCUP SAS healthcare analysis pandas
Platform: UNKNOWN
Classifier: Framework :: Django
Classifier: License :: OSI Approved :: MIT License
Classifier: Topic :: Scientific/Engineering
Requires: django (>= 1.6)
Requires: celery (>= 3.1.0)
Requires: pandas (>= 0.11.0)
Requires: pyhcup (>= 0.1.6)
Provides: djhcup_core
